{
  "id": "i1_08",
  "title": "上側確率点",
  "subtitle": "パーセント点",
  "estimated_minutes": 5,
  "category": "inference_1pop",
  "topic": "１つの母集団の母数に関する仮説検定の方法について理解する",
  "summary": "上側確率点について学びます。",
  "learning_objectives": [
    "上側確率点を理解できる"
  ],
  "prerequisites": [],
  "steps": [
    {
      "id": "i1_08_step01",
      "order": 1,
      "type": "text",
      "title": "はじめに",
      "body": "このレッスンは準備中です。"
    }
  ],
  "resources": {
    "key_terms": [
      "上側確率点"
    ],
    "external_links": []
  }
}